[
  {
    "name": "tim",
    "path": "img/tim/",
    "acts": [
      {
        "frame": 2,
        "id": "none",
        "loop": false,
        "scale": 0.6,
        "sheet": "none.png"
      },
      {
        "frame": 2,
        "id": "normal",
        "loop": false,
        "scale": 0.55,
        "sheet": "normal.png"
      },
      {
        "frame": 2,
        "id": "normal_g",
        "loop": false,
        "scale": 0.6,
        "sheet": "normal_g.png"
      },
      {
        "frame": 10,
        "id": "wink1",
        "loop": false,
        "scale": 0.6,
        "sheet": "wink1.png"
      },
      {
        "frame": 12,
        "id": "wink2",
        "loop": false,
        "scale": 0.6,
        "sheet": "wink2.png"
      }
    ]
  },
  {
    "name": "azuki",
    "path": "img/azuki/",
    "acts": [
      {
        "frame": 2,
        "id": "none",
        "loop": false,
        "scale": 0.6,
        "sheet": "none.png"
      },
      {
        "frame": 2,
        "id": "normal",
        "loop": false,
        "scale": 0.55,
        "sheet": "normal.png"
      },
      {
        "frame": 2,
        "id": "wink1",
        "loop": false,
        "scale": 0.6,
        "sheet": "wink1.png"
      }
    ]
  },
  {
    "name": "chalotte",
    "path": "img/chalotte/",
    "acts": [
      {
        "frame": 2,
        "id": "none",
        "loop": false,
        "scale": 0.6,
        "sheet": "none.png"
      },
      {
        "frame": 2,
        "id": "normal",
        "loop": false,
        "scale": 0.55,
        "sheet": "normal.png"
      }
    ]
  }
]